quicksamplemedinillag.py
quicksamplemedinillag-0.1.1.dist-info/LICENSE
quicksamplemedinillag-0.1.1.dist-info/METADATA
quicksamplemedinillag-0.1.1.dist-info/WHEEL
quicksamplemedinillag-0.1.1.dist-info/top_level.txt
quicksamplemedinillag-0.1.1.dist-info/RECORD
