Metadata-Version: 2.1
Name: quicksamplemedinillag
Version: 0.1.1
Summary: Quicksample Test Package for Data Demo
Author: Guillermo Medinilla
Classifier: Programming Language :: Python :: 3
Classifier: License :: OSI Approved :: MIT License
Classifier: Operating System :: OS Independent
Requires-Python: >=3.6
License-File: LICENSE
